CHANGES.txt
CONTRIBUTORS.txt
MANIFEST.in
README.txt
setup.py
src/collective/__init__.py
src/collective.forgetit.egg-info/PKG-INFO
src/collective.forgetit.egg-info/SOURCES.txt
src/collective.forgetit.egg-info/dependency_links.txt
src/collective.forgetit.egg-info/entry_points.txt
src/collective.forgetit.egg-info/namespace_packages.txt
src/collective.forgetit.egg-info/not-zip-safe
src/collective.forgetit.egg-info/requires.txt
src/collective.forgetit.egg-info/top_level.txt
src/collective/forgetit/__init__.py
src/collective/forgetit/configure.zcml
src/collective/forgetit/residue.pt
src/collective/forgetit/views.py
src/collective/forgetit/profiles/default/controlpanel.xml
src/collective/forgetit/profiles/default/metadata.xml