Metadata-Version: 1.1
Name: collective.forgetit
Version: 0.0.1
Summary: Remove uninstalled Products/package residue
Home-page: http://github.com/starzel/collective.forgetit
Author: Patrick Gerken
Author-email: gerken@patrick-gerken.de
License: BSD
Platform: UNKNOWN
Classifier: Framework :: Plone
Classifier: Programming Language :: Python
